GoZhuanjiaBiancheng/README.md
GoZhuanjiaBiancheng/__init__.py
GoZhuanjiaBiancheng/__main__.py
GoZhuanjiaBiancheng/file.epub
GoZhuanjiaBiancheng/index.html
GoZhuanjiaBiancheng/css/__init__.py
GoZhuanjiaBiancheng/css/annotations.css
GoZhuanjiaBiancheng/css/main.css
GoZhuanjiaBiancheng/css/normalize.css
GoZhuanjiaBiancheng/css/popup.css
GoZhuanjiaBiancheng/font/__init__.py
GoZhuanjiaBiancheng/font/fontello.eot
GoZhuanjiaBiancheng/font/fontello.svg
GoZhuanjiaBiancheng/font/fontello.ttf
GoZhuanjiaBiancheng/font/fontello.woff
GoZhuanjiaBiancheng/img/__init__.py
GoZhuanjiaBiancheng/img/annotator-glyph-sprite.png
GoZhuanjiaBiancheng/img/annotator-icon-sprite.png
GoZhuanjiaBiancheng/img/apple-touch-icon.png
GoZhuanjiaBiancheng/img/cancelfullscreen.png
GoZhuanjiaBiancheng/img/close.png
GoZhuanjiaBiancheng/img/fullscreen.png
GoZhuanjiaBiancheng/img/loader.gif
GoZhuanjiaBiancheng/img/menu-icon.png
GoZhuanjiaBiancheng/img/save.png
GoZhuanjiaBiancheng/img/saved.png
GoZhuanjiaBiancheng/img/settings-s.png
GoZhuanjiaBiancheng/img/settings.png
GoZhuanjiaBiancheng/img/star.png
GoZhuanjiaBiancheng/js/__init__.py
GoZhuanjiaBiancheng/js/epub.js
GoZhuanjiaBiancheng/js/epub.min.js
GoZhuanjiaBiancheng/js/epub.min.map
GoZhuanjiaBiancheng/js/hooks.min.js
GoZhuanjiaBiancheng/js/hooks.min.map
GoZhuanjiaBiancheng/js/reader.js
GoZhuanjiaBiancheng/js/reader.js.map
GoZhuanjiaBiancheng/js/reader.min.js
GoZhuanjiaBiancheng/js/reader.min.map
GoZhuanjiaBiancheng/js/hooks/__init__.py
GoZhuanjiaBiancheng/js/hooks/extensions/__init__.py
GoZhuanjiaBiancheng/js/hooks/extensions/highlight.js
GoZhuanjiaBiancheng/js/libs/__init__.py
GoZhuanjiaBiancheng/js/libs/jquery.min.js
GoZhuanjiaBiancheng/js/libs/localforage.min.js
GoZhuanjiaBiancheng/js/libs/screenfull.js
GoZhuanjiaBiancheng/js/libs/screenfull.min.js
GoZhuanjiaBiancheng/js/libs/zip.min.js
GoZhuanjiaBiancheng/js/plugins/__init__.py
GoZhuanjiaBiancheng/js/plugins/hypothesis.js
GoZhuanjiaBiancheng/js/plugins/search.js
go_zhuanjia_biancheng-2024.3.5.0.dist-info/METADATA
go_zhuanjia_biancheng-2024.3.5.0.dist-info/WHEEL
go_zhuanjia_biancheng-2024.3.5.0.dist-info/entry_points.txt
go_zhuanjia_biancheng-2024.3.5.0.dist-info/top_level.txt
go_zhuanjia_biancheng-2024.3.5.0.dist-info/RECORD
